LICENSE.txt
MANIFEST.in
README.rst
REQUIREMENTS.txt
VERSION.txt
setup.cfg
setup.py
craigslist/__init__.py
craigslist/__init__.pyc
craigslist/base.py
craigslist/base.pyc
craigslist/craigslist.py
craigslist/craigslist.pyc
craigslist/sites.pyc
craigslist/utils.py
craigslist/utils.pyc
craigslist/__pycache__/__init__.cpython-37.pyc
craigslist/__pycache__/base.cpython-37.pyc
craigslist/__pycache__/craigslist.cpython-37.pyc
craigslist/__pycache__/utils.cpython-37.pyc
python_craigslist.egg-info/PKG-INFO
python_craigslist.egg-info/SOURCES.txt
python_craigslist.egg-info/dependency_links.txt
python_craigslist.egg-info/requires.txt
python_craigslist.egg-info/top_level.txt