Metadata-Version: 1.1
Name: python-craigslist
Version: 1.0.9
Summary: Simple Craigslist wrapper.
Home-page: https://github.com/juliomalegria/python-craigslist
Author: Julio M Alegria
Author-email: juliomalegria@gmail.com
License: MIT-Zero
Download-URL: https://github.com/juliomalegria/python-craigslist/tarball/1.0.9
Platform: UNKNOWN
